proq/__init__.py
proq/collectible.py
proq/common.py
proq/proq.py
proq/transform.py
proq/transform_parallel.py
proq-0.0.4.dist-info/LICENSE
proq-0.0.4.dist-info/WHEEL
proq-0.0.4.dist-info/METADATA
proq-0.0.4.dist-info/RECORD
