Metadata-Version: 2.1
Name: proq
Version: 0.0.4
Summary: Process Queue
Author-email: Roi Gabay <roigby@gmail.com>
Requires-Python: >=3.9
Classifier: Programming Language :: Python :: 3
Classifier: License :: OSI Approved :: MIT License
Classifier: Operating System :: OS Independent
Requires-Dist: dill
Requires-Dist: black ; extra == "dev"
Requires-Dist: mypy ; extra == "dev"
Requires-Dist: pytest ; extra == "test"
Requires-Dist: pytest-cov ; extra == "test"
Project-URL: Bug Tracker, https://github.com/gabay/proq/issues
Project-URL: Home, https://github.com/gabay/proq
Provides-Extra: dev
Provides-Extra: test
